dash_chalice/__init__.py
dash_chalice/app.py
dash_chalice-0.1.1.dist-info/LICENSE
dash_chalice-0.1.1.dist-info/METADATA
dash_chalice-0.1.1.dist-info/WHEEL
dash_chalice-0.1.1.dist-info/top_level.txt
dash_chalice-0.1.1.dist-info/RECORD
