Metadata-Version: 2.1
Name: dash-chalice
Version: 0.1.1
Summary: Chalice as an alternative to Flask for Plotly Dash
Home-page: https://github.com/ellwise/dash-chalice
Author: Elliott Wise
Author-email: ell.wise@gmail.com
License: GNU GPL v3
Platform: UNKNOWN
License-File: LICENSE
Requires-Dist: dash
Requires-Dist: chalice
